NiceFlow/__init__.py
NiceFlow/cli/__init__.py
NiceFlow/cli/cli.py
NiceFlow/cluster/__init__.py
NiceFlow/cluster/master.py
NiceFlow/cluster/operator.py
NiceFlow/cluster/worker.py
NiceFlow/common/__init__.py
NiceFlow/common/ftp_util.py
NiceFlow/common/hdfs_util.py
NiceFlow/common/module_util.py
NiceFlow/core/__init__.py
NiceFlow/core/db_logging_handler.py
NiceFlow/core/db_plugin.py
NiceFlow/core/flow.py
NiceFlow/core/flow_log.py
NiceFlow/core/flow_log_handler.py
NiceFlow/core/functions.py
NiceFlow/core/manager.py
NiceFlow/core/mysqldb_logging_handler.py
NiceFlow/core/plugin.py
NiceFlow/core/plugin_field.py
NiceFlow/core/plugin_log.py
NiceFlow/core/plugin_time_record.py
NiceFlow/core/states.py
NiceFlow/core/tool.py
NiceFlow/core/exception/__init__.py
NiceFlow/core/exception/flow_exception.py
NiceFlow/core/exception/param_exception.py
NiceFlow/core/utils/__init__.py
NiceFlow/core/utils/encrypt_data.py
NiceFlow/log/__init__.py
NiceFlow/log/flow_log.py
NiceFlow/log/flow_log_handler.py
NiceFlow/log/mysqldb_logging_handler.py
NiceFlow/log/plugin_log.py
NiceFlow/plugins/__init__.py
NiceFlow/plugins/add_field.py
NiceFlow/plugins/agg.py
NiceFlow/plugins/akshare_input.py
NiceFlow/plugins/ck_input.py
NiceFlow/plugins/ck_output.py
NiceFlow/plugins/console.py
NiceFlow/plugins/cos_input.py
NiceFlow/plugins/cos_output.py
NiceFlow/plugins/csv_input.py
NiceFlow/plugins/csv_output.py
NiceFlow/plugins/db2_input.py
NiceFlow/plugins/db2_output.py
NiceFlow/plugins/db_execute.py
NiceFlow/plugins/duckdb_input.py
NiceFlow/plugins/duckdb_output.py
NiceFlow/plugins/duplicate.py
NiceFlow/plugins/email.py
NiceFlow/plugins/es_input.py
NiceFlow/plugins/es_output.py
NiceFlow/plugins/excel_input.py
NiceFlow/plugins/excel_output.py
NiceFlow/plugins/faker_input.py
NiceFlow/plugins/filter.py
NiceFlow/plugins/for.py
NiceFlow/plugins/frame_input.py
NiceFlow/plugins/ftp_input.py
NiceFlow/plugins/ftp_output.py
NiceFlow/plugins/function.py
NiceFlow/plugins/hdfs_input.py
NiceFlow/plugins/hdfs_output.py
NiceFlow-0.0.7.dist-info/LICENSE
NiceFlow-0.0.7.dist-info/METADATA
NiceFlow-0.0.7.dist-info/WHEEL
NiceFlow-0.0.7.dist-info/entry_points.txt
NiceFlow-0.0.7.dist-info/top_level.txt
NiceFlow-0.0.7.dist-info/RECORD
