Metadata-Version: 2.1
Name: NiceFlow
Version: 0.0.7
Summary: ETL数据处理/数据迁移/数据分析工具
Home-page: https://www.seeoo.top
Author: BleethNie
Author-email: xiao5406710@foxmail.com
Platform: python3
Requires-Python: >=3.8
License-File: LICENSE
Requires-Dist: duckdb >=0.10.1
Requires-Dist: pandas >=2.1.0
Requires-Dist: loguru >=0.7.2
Requires-Dist: click >=8.1.7
Requires-Dist: blinker >=1.7.0
Requires-Dist: pycryptodome ==3.20.0
